filedialpy/__init__.py
filedialpy/linux_kdialog.py
filedialpy/linux_tkinter.py
filedialpy/linux_zenity.py
filedialpy/mac.py
filedialpy/windows.py
filedialpy-1.3.3.dist-info/LICENSE
filedialpy-1.3.3.dist-info/METADATA
filedialpy-1.3.3.dist-info/WHEEL
filedialpy-1.3.3.dist-info/top_level.txt
filedialpy-1.3.3.dist-info/RECORD
