Metadata-Version: 2.1
Name: filedialpy
Version: 1.3.3
Summary: Package for opening native file dialogs on linux, macOS and windows.
Author: Etienne Sollier
Project-URL: Homepage, https://github.com/e-sollier/filedialpy
Classifier: Programming Language :: Python :: 3
Classifier: Operating System :: OS Independent
Requires-Python: >=3.3
License-File: LICENSE
Requires-Dist: pywin32 ; platform_system == "Windows"
